LICENSE.md
MANIFEST.in
setup.py
waf
wscript
Flappy.egg-info/PKG-INFO
Flappy.egg-info/SOURCES.txt
Flappy.egg-info/dependency_links.txt
Flappy.egg-info/top_level.txt
_core/_core.pyx
_core/directrenderer.pxi
_core/display.pxi
_core/event.pxi
_core/geom.pxi
_core/graphics.pxi
_core/matrix.pxi
_core/object.pxi
_core/surface.pxi
_core/textfield.pxi
_core/tilesheet.pxi
_core/wscript
_gl/_gl.pyx
_gl/cdefs.pxd
_gl/constants.pxi
_gl/extensions.h
_gl/objects.pxi
_gl/wscript
flappy/__init__.py
flappy/__version__.py
flappy/display/__init__.py
flappy/display/bitmap.py
flappy/display/bitmapdata.py
flappy/display/directrenderer.py
flappy/display/displayobject.py
flappy/display/displayobjectcontainer.py
flappy/display/fps.py
flappy/display/graphics.py
flappy/display/interactiveobject.py
flappy/display/sprite.py
flappy/display/stage.py
flappy/display/tilesheet.py
flappy/display3d/__init__.py
flappy/display3d/indexbuffer3d.py
flappy/display3d/program3d.py
flappy/display3d/scene3d.py
flappy/display3d/texture.py
flappy/display3d/vertexbuffer3d.py
flappy/events/__init__.py
flappy/events/event.py
flappy/events/eventdispatcher.py
flappy/events/focusevent.py
flappy/events/keyboardevent.py
flappy/events/mouseevent.py
flappy/events/touchevent.py
flappy/geom/__init__.py
flappy/geom/colortransform.py
flappy/geom/matrix.py
flappy/geom/matrix3d.py
flappy/geom/point.py
flappy/geom/rectangle.py
flappy/geom/transform.py
flappy/text/__init__.py
flappy/text/font.py
flappy/text/textfield.py
flappy/text/textformat.py
flappy/text/textlinemetrics.py
flappy/ui/__init__.py
flappy/ui/keyboard.py
flappy/ui/mouse.py
openfl_lime/wscript
openfl_lime/include/Audio.h
openfl_lime/include/ByteArray.h
openfl_lime/include/CachedExtent.h
openfl_lime/include/Display.h
openfl_lime/include/ExternalInterface.h
openfl_lime/include/Filters.h
openfl_lime/include/Font.h
openfl_lime/include/Geom.h
openfl_lime/include/Graphics.h
openfl_lime/include/Input.h
openfl_lime/include/KeyCodes.h
openfl_lime/include/LimeThread.h
openfl_lime/include/Lzma.h
openfl_lime/include/Matrix.h
openfl_lime/include/Object.h
openfl_lime/include/Pixel.h
