Metadata-Version: 1.1
Name: Flappy
Version: 0.3.7
Summary: Multimedia library with the Adobe Flash-like API
Home-page: https://github.com/pyronimous/flappy
Author: Michael P.
Author-email: pyronimous@gmail.com
License: MIT
Platform: UNKNOWN
Classifier: Development Status :: 3 - Alpha
Classifier: Intended Audience :: Developers
Classifier: License :: OSI Approved :: MIT License
Classifier: Operating System :: OS Independent
Classifier: Topic :: Multimedia :: Graphics
Classifier: Topic :: Games/Entertainment
Classifier: Topic :: Software Development :: Libraries :: Python Modules
